mrender/.md5
mrender/__about__.py
mrender/__init__.py
mrender/docs2md.py
mrender/extract_docs.py
mrender/h5
mrender/live_pane.py
mrender/main.py
mrender/md.py
mrender/panel.py
mrender/python2json.py
mrender/render.py
mrender/requirements.txt
mrender/web.py
mrender/web2md.py
mrender-1.0.234.dist-info/METADATA
mrender-1.0.234.dist-info/WHEEL
mrender-1.0.234.dist-info/entry_points.txt
mrender-1.0.234.dist-info/licenses/LICENSE
mrender-1.0.234.dist-info/RECORD
